ptx.py
setup.py
ptx.egg-info/PKG-INFO
ptx.egg-info/SOURCES.txt
ptx.egg-info/dependency_links.txt
ptx.egg-info/top_level.txt