Metadata-Version: 1.0
Name: ptx
Version: 1.1
Summary: A utility code for PTX authorization.
Home-page: https://github.com/yuzzwx/PTX
Author: yuzzwx
Author-email: yuzzwx@gmail.com
License: MIT
Platform: UNKNOWN
